CoinCrypt/Coincrypt.py
CoinCrypt/__init__.py
CoinCrypt-0.0.2.10.0.dist-info/LICENSE
CoinCrypt-0.0.2.10.0.dist-info/METADATA
CoinCrypt-0.0.2.10.0.dist-info/WHEEL
CoinCrypt-0.0.2.10.0.dist-info/top_level.txt
CoinCrypt-0.0.2.10.0.dist-info/RECORD
