Metadata-Version: 2.1
Name: CoinCrypt
Version: 0.0.2.10.0
Summary: Simple methods for working with coinmarketcap API
Home-page: UNKNOWN
Author: Henrique Domiciano Osinski
Author-email: <henriquedomiciano@yahoo.com>
License: UNKNOWN
Platform: UNKNOWN
Classifier: Development Status :: 3 - Alpha
Classifier: Programming Language :: Python :: 3
Classifier: Operating System :: Unix
Classifier: Operating System :: MacOS :: MacOS X
Classifier: Operating System :: Microsoft :: Windows
License-File: LICENSE
Requires-Dist: requests
